{"path":"src/llamas","relativePath":"src/llamas","name":"llamas","type":"folder","children":[{"path":"src/llamas/1.jpg","relativePath":"src/llamas/1.jpg","name":"1.jpg","type":"file"},{"path":"src/llamas/10.jpg","relativePath":"src/llamas/10.jpg","name":"10.jpg","type":"file"},{"path":"src/llamas/11.jpg","relativePath":"src/llamas/11.jpg","name":"11.jpg","type":"file"},{"path":"src/llamas/12.jpg","relativePath":"src/llamas/12.jpg","name":"12.jpg","type":"file"},{"path":"src/llamas/13.jpg","relativePath":"src/llamas/13.jpg","name":"13.jpg","type":"file"},{"path":"src/llamas/14.jpg","relativePath":"src/llamas/14.jpg","name":"14.jpg","type":"file"},{"path":"src/llamas/15.jpg","relativePath":"src/llamas/15.jpg","name":"15.jpg","type":"file"},{"path":"src/llamas/16.jpg","relativePath":"src/llamas/16.jpg","name":"16.jpg","type":"file"},{"path":"src/llamas/17.jpg","relativePath":"src/llamas/17.jpg","name":"17.jpg","type":"file"},{"path":"src/llamas/18.jpg","relativePath":"src/llamas/18.jpg","name":"18.jpg","type":"file"},{"path":"src/llamas/19.jpg","relativePath":"src/llamas/19.jpg","name":"19.jpg","type":"file"},{"path":"src/llamas/2.jpg","relativePath":"src/llamas/2.jpg","name":"2.jpg","type":"file"},{"path":"src/llamas/20.jpg","relativePath":"src/llamas/20.jpg","name":"20.jpg","type":"file"},{"path":"src/llamas/21.jpg","relativePath":"src/llamas/21.jpg","name":"21.jpg","type":"file"},{"path":"src/llamas/22.jpg","relativePath":"src/llamas/22.jpg","name":"22.jpg","type":"file"},{"path":"src/llamas/23.jpg","relativePath":"src/llamas/23.jpg","name":"23.jpg","type":"file"},{"path":"src/llamas/24.jpg","relativePath":"src/llamas/24.jpg","name":"24.jpg","type":"file"},{"path":"src/llamas/25.jpg","relativePath":"src/llamas/25.jpg","name":"25.jpg","type":"file"},{"path":"src/llamas/26.jpg","relativePath":"src/llamas/26.jpg","name":"26.jpg","type":"file"},{"path":"src/llamas/27.jpg","relativePath":"src/llamas/27.jpg","name":"27.jpg","type":"file"},{"path":"src/llamas/28.JPG","relativePath":"src/llamas/28.JPG","name":"28.JPG","type":"file"},{"path":"src/llamas/29.jpg","relativePath":"src/llamas/29.jpg","name":"29.jpg","type":"file"},{"path":"src/llamas/3.jpg","relativePath":"src/llamas/3.jpg","name":"3.jpg","type":"file"},{"path":"src/llamas/30.jpg","relativePath":"src/llamas/30.jpg","name":"30.jpg","type":"file"},{"path":"src/llamas/31.jpg","relativePath":"src/llamas/31.jpg","name":"31.jpg","type":"file"},{"path":"src/llamas/32.jpg","relativePath":"src/llamas/32.jpg","name":"32.jpg","type":"file"},{"path":"src/llamas/33.JPG","relativePath":"src/llamas/33.JPG","name":"33.JPG","type":"file"},{"path":"src/llamas/34.jpg","relativePath":"src/llamas/34.jpg","name":"34.jpg","type":"file"},{"path":"src/llamas/35.JPG","relativePath":"src/llamas/35.JPG","name":"35.JPG","type":"file"},{"path":"src/llamas/36.jpg","relativePath":"src/llamas/36.jpg","name":"36.jpg","type":"file"},{"path":"src/llamas/37.jpg","relativePath":"src/llamas/37.jpg","name":"37.jpg","type":"file"},{"path":"src/llamas/38.jpg","relativePath":"src/llamas/38.jpg","name":"38.jpg","type":"file"},{"path":"src/llamas/39.jpg","relativePath":"src/llamas/39.jpg","name":"39.jpg","type":"file"},{"path":"src/llamas/4.jpg","relativePath":"src/llamas/4.jpg","name":"4.jpg","type":"file"},{"path":"src/llamas/40.jpg","relativePath":"src/llamas/40.jpg","name":"40.jpg","type":"file"},{"path":"src/llamas/42.jpg","relativePath":"src/llamas/42.jpg","name":"42.jpg","type":"file"},{"path":"src/llamas/43.JPG","relativePath":"src/llamas/43.JPG","name":"43.JPG","type":"file"},{"path":"src/llamas/44.jpg","relativePath":"src/llamas/44.jpg","name":"44.jpg","type":"file"},{"path":"src/llamas/45.JPG","relativePath":"src/llamas/45.JPG","name":"45.JPG","type":"file"},{"path":"src/llamas/46.jpg","relativePath":"src/llamas/46.jpg","name":"46.jpg","type":"file"},{"path":"src/llamas/47.jpg","relativePath":"src/llamas/47.jpg","name":"47.jpg","type":"file"},{"path":"src/llamas/48.JPG","relativePath":"src/llamas/48.JPG","name":"48.JPG","type":"file"},{"path":"src/llamas/49.JPG","relativePath":"src/llamas/49.JPG","name":"49.JPG","type":"file"},{"path":"src/llamas/5.jpg","relativePath":"src/llamas/5.jpg","name":"5.jpg","type":"file"},{"path":"src/llamas/50.jpg","relativePath":"src/llamas/50.jpg","name":"50.jpg","type":"file"},{"path":"src/llamas/51.JPG","relativePath":"src/llamas/51.JPG","name":"51.JPG","type":"file"},{"path":"src/llamas/52.jpg","relativePath":"src/llamas/52.jpg","name":"52.jpg","type":"file"},{"path":"src/llamas/53.jpg","relativePath":"src/llamas/53.jpg","name":"53.jpg","type":"file"},{"path":"src/llamas/54.jpg","relativePath":"src/llamas/54.jpg","name":"54.jpg","type":"file"},{"path":"src/llamas/55.JPG","relativePath":"src/llamas/55.JPG","name":"55.JPG","type":"file"},{"path":"src/llamas/56.jpg","relativePath":"src/llamas/56.jpg","name":"56.jpg","type":"file"},{"path":"src/llamas/6.jpg","relativePath":"src/llamas/6.jpg","name":"6.jpg","type":"file"},{"path":"src/llamas/7.jpg","relativePath":"src/llamas/7.jpg","name":"7.jpg","type":"file"},{"path":"src/llamas/8.jpg","relativePath":"src/llamas/8.jpg","name":"8.jpg","type":"file"},{"path":"src/llamas/9.jpg","relativePath":"src/llamas/9.jpg","name":"9.jpg","type":"file"}]}